{
  "project_info": {
    "project_number": "518420891622",
    "firebase_url": "https://grabalorry.firebaseio.com",
    "project_id": "grabalorry",
    "storage_bucket": "grabalorry.appspot.com"
  },
  "client": [
    {
      "client_info": {
        "mobilesdk_app_id": "1:518420891622:android:899b8db422987fe3",
        "android_client_info": {
          "package_name": "com.example.owner.grabalorry"
        }
      },
      "oauth_client": [
        {
          "client_id": "518420891622-h8qh20atnltujhesdjpg109or65jdqi4.apps.googleusercontent.com",
          "client_type": 3
        }
      ],
      "api_key": [
        {
          "current_key": "AIzaSyB7Aue19XBn2kH3b3PNTzfDIqrF8bebiGo"
        }
      ],
      "services": {
        "analytics_service": {
          "status": 1
        },
        "appinvite_service": {
          "status": 1,
          "other_platform_oauth_client": []
        },
        "ads_service": {
          "status": 2
        }
      }
    }
  ],
  "configuration_version": "1"
}